{
    "urlName": "floating-molten-lava-orb-ac",
    "url": "http://aqwwiki.wikidot.com/floating-molten-lava-orb-ac",
    "name": "Floating Molten Lava Orb (AC)",
    "type": "capes_&_back_items",
    "description": "Lava is called magma until it reaches the surface of Lore and meets the air. It's destructive if flung at an enemy or city, but even left alone, it eats air until there's nothing left to breathe.",
    "rarity": "Rare Rarity",
    "tags": [
        "Adventure Coins",
        "Rare"
    ],
    "images": [
        "https://i.imgur.com/iGehOSN.png"
    ],
    "hash": "00cd5ef44858ffe2046c72486880f981"
}