{
    "urlName": "leanan-sidhe-s-glories",
    "url": "http://aqwwiki.wikidot.com/leanan-sidhe-s-glories",
    "name": "Leanan Sidhe's Glories",
    "type": "capes_&_back_items",
    "description": "\ufeffCertain butterflies will drink blood, sweat, and tears. Leanan Sidhe's victims are deprived of all three as they wither and die. Colorful scales dot their death beds.",
    "rarity": "Rare Rarity",
    "tags": [
        "Adventure Coins",
        "Rare"
    ],
    "images": [
        "https://imgur.com/eXhgRKl.png"
    ],
    "hash": "10a2c3e623d0234dbbc7b9b29c888920"
}