{
    "urlName": "fest-ebil-turret-0-ac",
    "url": "http://aqwwiki.wikidot.com/fest-ebil-turret-0-ac",
    "name": "Fest-EBIL Turret (0 AC)",
    "type": "capes_&_back_items",
    "description": "Having this baby on standby keeps conversations respectful (Click to fire lazers).",
    "rarity": "Rare Rarity",
    "tags": [
        "Adventure Coins",
        "Pseudo Rare"
    ],
    "images": [
        "https://imgur.com/3Fcgeuc.png",
        "https://i.imgur.com/C6Td8ad.png"
    ],
    "hash": "2f17cc65abaeacbe80f38a9fdb55a409"
}