{
    "urlName": "orange-dragon-s-accoutrements-0-ac",
    "url": "http://aqwwiki.wikidot.com/orange-dragon-s-accoutrements-0-ac",
    "name": "Orange Dragon's Accoutrements (0 AC)",
    "type": "capes_&_back_items",
    "description": "There be nothin' better than sailing off into the sunset. This be a reminder not all days be filled",
    "rarity": "Awesome Rarity",
    "tags": [
        "Adventure Coins",
        "Pseudo Rare"
    ],
    "images": [
        "https://i.imgur.com/UyK6MSt.png"
    ],
    "hash": "325eeb6321e14b3704fcdb7f4b6bdfe6"
}