{
    "urlName": "bloodletter-sacrifice-portal-0-ac",
    "url": "http://aqwwiki.wikidot.com/bloodletter-sacrifice-portal-0-ac",
    "name": "Bloodletter Sacrifice Portal (0 AC)",
    "type": "capes_&_back_items",
    "description": "Drench it in fresh blood, and a being of sacrifice and death will be called to usher your enemies to the Underworld.",
    "rarity": "Rare Rarity",
    "tags": [
        "Adventure Coins",
        "Pseudo Rare"
    ],
    "images": [
        "https://i.imgur.com/3gjhN47.png"
    ],
    "hash": "3d8ba36d3b475d547b0affd88cb6d47f"
}