{
    "urlName": "draconic-chronomancer-s-wings",
    "url": "http://aqwwiki.wikidot.com/draconic-chronomancer-s-wings",
    "name": "Draconic Chronomancer's Wings",
    "type": "capes_&_back_items",
    "description": "Draconic Chronomancers control the flow of time, causing it to circle back upon itself to make changes to the past\u2026 and future.",
    "rarity": "Collector's Rare Rarity",
    "tags": [
        "Adventure Coins",
        "Special Offer"
    ],
    "images": [
        "https://i.imgur.com/vrIkKIa.png"
    ],
    "hash": "42ed3fe260ffe4d0dc4e535913451bfc"
}