{
    "urlName": "golden-dragonborn-tail-non-ac",
    "url": "http://aqwwiki.wikidot.com/golden-dragonborn-tail-non-ac",
    "name": "Golden Dragonborn Tail (Non-AC)",
    "type": "capes_&_back_items",
    "description": "The Dragonborn are two thirds Dragon, and one third anything else. This is apparently worth bragging about.",
    "rarity": "Rare Rarity",
    "tags": [
        "Rare"
    ],
    "images": [
        "https://i.imgur.com/oKKymaS.png"
    ],
    "hash": "6769c6e9bfa10c8807b7cda3cd28e6de"
}