{
    "urlName": "silver-horned-dragon-companion-0-ac",
    "url": "http://aqwwiki.wikidot.com/silver-horned-dragon-companion-0-ac",
    "name": "Silver Horned Dragon Companion (0 AC)",
    "type": "capes_&_back_items",
    "description": "Yarrrr! Most landlubbers never hear of th' fleet o' ships the DragonLords command. But th' dragon companions be fearsome fighters on land, sea, AND air.",
    "rarity": "Rare Rarity",
    "tags": [
        "Adventure Coins",
        "Pseudo Rare"
    ],
    "images": [
        "https://i.imgur.com/CCvJqBH.png"
    ],
    "hash": "763a8f19f9a5531479c6b6614a01a89b"
}