{
    "urlName": "seraphic-naval-commander-s-parrot-legend",
    "url": "http://aqwwiki.wikidot.com/seraphic-naval-commander-s-parrot-legend",
    "name": "Seraphic Naval Commander's Parrot (Legend)",
    "type": "capes_&_back_items",
    "description": "Naval Commanders devoted to Laken don't need to loot and plunder hapless villagers for booty. All they ask is for their leader's loyalty and stolen Legion treasures in exchange for their services.",
    "rarity": "Rare Rarity",
    "tags": [
        "Legend",
        "Rare"
    ],
    "images": [
        "https://i.imgur.com/hjtG13m.png",
        "https://i.imgur.com/4sCqOwp.png"
    ],
    "hash": "81b63a4d8e0a506fa4e3a4a8e00ca987"
}