{
    "urlName": "enchanted-tora-guardian",
    "url": "http://aqwwiki.wikidot.com/enchanted-tora-guardian",
    "name": "Enchanted Tora Guardian",
    "type": "capes_&_back_items",
    "description": "Elaborate armor worn by only the highest level of Akiban defenders. (Item is CC)",
    "rarity": "Legendary Item Rarity",
    "tags": [
        "Adventure Coins",
        "Special Offer"
    ],
    "images": [
        "https://i.imgur.com/BETsu25.png"
    ],
    "hash": "828d10f62b74f2955e179d03cb0b3754"
}