{
    "urlName": "the-cape-of-the-divine",
    "url": "http://aqwwiki.wikidot.com/the-cape-of-the-divine",
    "name": "The Cape of the Divine",
    "type": "capes_&_back_items",
    "description": "Only the omnipotent ones will be able to grace their friends while wearing this holy cape.",
    "rarity": "Awesome Rarity",
    "tags": [
        "Adventure Coins",
        "Legend"
    ],
    "images": [
        "http://i.imgur.com/79s3BE0.png"
    ],
    "hash": "9620d0f8ca17e65015c79340d889468f"
}