{
    "urlName": "oathkeeper-halo-legend",
    "url": "http://aqwwiki.wikidot.com/oathkeeper-halo-legend",
    "name": "OathKeeper Halo (Legend)",
    "type": "capes_&_back_items",
    "description": "Don't be deceived by it's shining light. Instead, pay heed to the sickening feeling that rises in your throat whenever you look at it. Beware this profane symbol!",
    "rarity": "Rare Rarity",
    "tags": [
        "Legend",
        "Rare"
    ],
    "images": [],
    "hash": "9de2eb9d5700cac54f31f2578d2468d3"
}