{
    "urlName": "closed-lunar-sandwings-ac",
    "url": "http://aqwwiki.wikidot.com/closed-lunar-sandwings-ac",
    "name": "Closed Lunar Sandwings (AC)",
    "type": "capes_&_back_items",
    "description": "Wings furled, you might be grounded but you are still very stylish while wearing these lovely, lunar wings!",
    "rarity": "Rare Rarity",
    "tags": [
        "Adventure Coins",
        "Rare"
    ],
    "images": [
        "http://aqwwiki.wdfiles.com/local--files/closed-lunar-sandwings-ac/ClosedLunarSandwings.png"
    ],
    "hash": "bf008d4ff1fb445c36b15ae97f772a8a"
}