{
    "urlName": "obsidian-dragon-s-baby-companion-0-ac",
    "url": "http://aqwwiki.wikidot.com/obsidian-dragon-s-baby-companion-0-ac",
    "name": "Obsidian Dragon's Baby Companion (0 AC)",
    "type": "capes_&_back_items",
    "description": "Gold never tarnishes. Your companion will accompany you until the farthest horizon is reached.",
    "rarity": "Rare Rarity",
    "tags": [
        "Adventure Coins"
    ],
    "images": [
        "https://i.imgur.com/PaQ0Daa.png"
    ],
    "hash": "cb244180a5feeb9ae8e439ff208bce7e"
}