{
    "urlName": "grimblight-commander-s-spectre-0-ac",
    "url": "http://aqwwiki.wikidot.com/grimblight-commander-s-spectre-0-ac",
    "name": "GrimBlight Commander's Spectre (0 AC)",
    "type": "capes_&_back_items",
    "description": "A victim of the ship-shaped dungeon, chained to its hull as a ghostly deckhand. They grasp at new challengers, and drag them to their doom desperately needing extra hands to swab the decks.",
    "rarity": "Rare Rarity",
    "tags": [
        "Adventure Coins",
        "Pseudo Rare"
    ],
    "images": [
        "https://i.imgur.com/UM2waNh.png"
    ],
    "hash": "d034205084485678e8770adcdabf7c35"
}