{
    "urlName": "raptor-rider-s-backblades",
    "url": "http://aqwwiki.wikidot.com/raptor-rider-s-backblades",
    "name": "Raptor Rider's Backblades",
    "type": "capes_&_back_items",
    "description": "The cores of these blades burn blue and white, feeding off the rage the raptor feels at being ridden. Don't let them burn your back.",
    "rarity": "Rare Rarity",
    "tags": [
        "Adventure Coins",
        "Rare"
    ],
    "images": [
        "http://aqwwiki.wdfiles.com/local--files/raptor-rider-s-backblades/RRB.png"
    ],
    "hash": "d7b9d60c5e41161625f82590c510b4fb"
}