{
    "urlName": "looming-legion-paragon",
    "url": "http://aqwwiki.wikidot.com/looming-legion-paragon",
    "name": "Looming Legion Paragon",
    "type": "capes_&_back_items",
    "description": "MWAAHAHAAHA. Dage the Evil is pleased with your contribution to the Undead Legion. Congratz on making it to the finals in the Dage Fan Art Contest, and keep up the amazing work. Long live the Undead Legion\u2026and your artwork!.",
    "rarity": "Legendary Item Rarity",
    "tags": [
        "Adventure Coins",
        "Rare",
        "Special Offer"
    ],
    "images": [
        "http://aqwwiki.wdfiles.com/local--files/looming-legion-paragon/LoomingLegionParagon.png"
    ],
    "hash": "f57a016fa9466eed580a43af92444a28"
}