{
    "urlName": "shadow-oathkeeper",
    "url": "http://aqwwiki.wikidot.com/shadow-oathkeeper",
    "name": "Shadow Oathkeeper",
    "type": "armors",
    "description": "Have you ever wondered what it is that nightmares are made of? Have you ever given thought to the main component of fear? Look into the darkness of Oathkeeper. Now you know. Suggested by fellow AQW hero, Xerxez, this year, and many others in the past.",
    "rarity": "Rare Rarity",
    "tags": [
        "Adventure Coins",
        "Rare"
    ],
    "images": [
        "https://i.imgur.com/9MNMeQB.png",
        "https://i.imgur.com/It8xsbI.png"
    ],
    "hash": "07a27c6665b0aa0fe9fefbf0e8772a1b"
}