{
    "urlName": "luminous-dragonknight",
    "url": "http://aqwwiki.wikidot.com/luminous-dragonknight",
    "name": "Luminous Dragonknight",
    "type": "armors",
    "description": "Lord SlayR took the power and might of the dragon and infused it with the light of the moon to give you a potent protection in the midst of battle. His suggestion is illuminated, powerful and enlightened.",
    "rarity": "Awesome Rarity",
    "tags": [
        "Adventure Coins"
    ],
    "images": [
        "http://i.imgur.com/vwxpqmo.png",
        "http://i.imgur.com/zECfpbv.png"
    ],
    "hash": "199c9a558894422b43898194a829ee77"
}