{
    "urlName": "pretty-pirate-captain-0-ac",
    "url": "http://aqwwiki.wikidot.com/pretty-pirate-captain-0-ac",
    "name": "Pretty Pirate Captain (0 AC)",
    "type": "armors",
    "description": "You can't be the pirate captain and not take the opportunity to be cute about it.",
    "rarity": "Rare Rarity",
    "tags": [
        "Adventure Coins",
        "Pseudo Rare"
    ],
    "images": [
        "https://i.imgur.com/EBblwsR.png",
        "https://i.imgur.com/an0rY8M.png"
    ],
    "hash": "285c6c1c6fedbafa1af5f5cf55fbfec3"
}