{
    "urlName": "skye-warden-of-the-west",
    "url": "http://aqwwiki.wikidot.com/skye-warden-of-the-west",
    "name": "Skye Warden of the West",
    "type": "armors",
    "description": "A title and role given to the second born of Skye's Ruler, tasked with executing the will of the crown. They strike faster than lightning, silencing any threat to their homeland's harmony.",
    "rarity": "Awesome Rarity",
    "tags": [
        "Adventure Coins"
    ],
    "images": [
        "https://i.imgur.com/KOBiXGp.png",
        "https://i.imgur.com/LAu8ndc.png"
    ],
    "hash": "3ddeda479766e241865d7d79b0843a63"
}