{
    "urlName": "evil-j-sixth-lord",
    "url": "http://aqwwiki.wikidot.com/evil-j-sixth-lord",
    "name": "Evil J-Sixth Lord",
    "type": "armors",
    "description": "\"It is not necessary to lie to achieve anything of value. A skilled Sixth-Lord is nearly impossible to defeat.\"",
    "rarity": "Awesome Rarity",
    "tags": [
        "Adventure Coins"
    ],
    "images": [
        "https://i.imgur.com/M2DbdXk.png",
        "https://i.imgur.com/79JwVlx.png"
    ],
    "hash": "4379d509a88fa59195fbe80f5028d63d"
}