{
    "urlName": "frostval-naval-commandeer",
    "url": "http://aqwwiki.wikidot.com/frostval-naval-commandeer",
    "name": "Frostval Naval CommanDEER",
    "type": "armors",
    "description": "If the seven seas freeze over, it's not the end of the world\u2026 it just means celebrating Frostval out on the open waters. Dress to match the season.",
    "rarity": "Legendary Item Rarity",
    "tags": [
        "Adventure Coins",
        "Pseudo Rare"
    ],
    "images": [
        "https://i.imgur.com/pJd7Y2U.png",
        "https://i.imgur.com/Oa41qsj.png",
        "https://i.imgur.com/KmAavt7.png",
        "https://i.imgur.com/Nfdnt78.png"
    ],
    "hash": "46497138df3fb657fe8ad012cbf4e7d3"
}