{
    "urlName": "diabolical-warden",
    "url": "http://aqwwiki.wikidot.com/diabolical-warden",
    "name": "Diabolical Warden",
    "type": "armors",
    "description": "Always in an everlasting shift, these overseers will be destined to serve the council and keep their eldritch inmates under control until they take their last breath.",
    "rarity": "Awesome Rarity",
    "tags": [
        "Adventure Coins"
    ],
    "images": [
        "https://i.imgur.com/i3mJdig.png",
        "https://i.imgur.com/2GGaaau.png"
    ],
    "hash": "50b733eab8279626850c189a8367ed66"
}