{
    "urlName": "pink-lightcaster-0-ac",
    "url": "http://aqwwiki.wikidot.com/pink-lightcaster-0-ac",
    "name": "Pink LightCaster (0 AC)",
    "type": "armors",
    "description": "The Order of the Pink LightCasters formed to support the Champion of Beauty and Light, and need every mage available to fight the battle against Chaorruption!",
    "rarity": "Rare Rarity",
    "tags": [
        "Adventure Coins",
        "Pseudo Rare"
    ],
    "images": [
        "https://i.imgur.com/a1SIJ7K.png",
        "https://i.imgur.com/eHQq5Fj.png",
        "https://i.imgur.com/wRTshLH.png",
        "https://i.imgur.com/zIlFlM8.png"
    ],
    "hash": "6bf1693652e991d31b9e64449c159dcb"
}