{
    "urlName": "dark-shadowslayer-z-ac",
    "url": "http://aqwwiki.wikidot.com/dark-shadowslayer-z-ac",
    "name": "Dark ShadowSlayer Z (AC)",
    "type": "armors",
    "description": "Don't these super-shady garments to sneak into your local inn shop and grab your anticipated items without paying a large piggy bank.",
    "rarity": "Rare Rarity",
    "tags": [
        "Adventure Coins",
        "Rare"
    ],
    "images": [
        "https://i.imgur.com/vRBKBX8.png",
        "https://i.imgur.com/VHgwyCq.png"
    ],
    "hash": "70afb71d4461c741eb1471f458494302"
}