{
    "urlName": "gold-doomknight-armor",
    "url": "http://aqwwiki.wikidot.com/gold-doomknight-armor",
    "name": "Gold DoomKnight Armor",
    "type": "armors",
    "description": "Not all DoomKnights are completely Evil\u2014some follow the Golden Rule. You must have one of the more pure souls.",
    "rarity": "Weird Rarity",
    "tags": [
        "Adventure Coins"
    ],
    "images": [
        "http://i.imgur.com/M9TLz0a.png",
        "http://i.imgur.com/27OW6W6.png"
    ],
    "hash": "743c529eeef10112970ff23309ca3a70"
}