{
    "urlName": "shadow-breather",
    "url": "http://aqwwiki.wikidot.com/shadow-breather",
    "name": "Shadow Breather",
    "type": "armors",
    "description": "Once it wears its blindfold, it will remove its mouth cover. Opening his mouth, he breathes an immense amount of shadow which will envelop the entire place in total darkness, enabling him to assassinate his opponent. His blades never shine for maximum stealth. -Ninjudo",
    "rarity": "Awesome Rarity",
    "tags": [
        "Adventure Coins"
    ],
    "images": [
        "http://i.imgur.com/tVTBB8N.png",
        "http://i.imgur.com/KJY0Ylm.png"
    ],
    "hash": "7b55fedae31476a009a4aa399269abe0"
}