{
    "urlName": "sandsea-harpyslayer",
    "url": "http://aqwwiki.wikidot.com/sandsea-harpyslayer",
    "name": "Sandsea HarpySlayer",
    "type": "armors",
    "description": "A special unit of assassins answering only to the Sandsea Generals, these HarpySlayer's are sent after only the most difficult of foes.",
    "rarity": "Awesome Rarity",
    "tags": [],
    "images": [
        "https://imgur.com/wgpACU7.png",
        "https://imgur.com/iLJjUau.png"
    ],
    "hash": "90bdd4876c0441276ad90229e0443335"
}