{
    "urlName": "dark-necrorocker",
    "url": "http://aqwwiki.wikidot.com/dark-necrorocker",
    "name": "Dark NecroRocker",
    "type": "armors",
    "description": "\ufeffTheir rock music is banned anywhere the sun still touches, but even the paladin order can't stop their fans from rushing to their doomed stages.",
    "rarity": "Awesome Rarity",
    "tags": [
        "Adventure Coins"
    ],
    "images": [
        "https://imgur.com/K8J8trb.png",
        "https://imgur.com/JfXDf7D.png"
    ],
    "hash": "a54d267aba7ad66469299dc8e642aff9"
}