{
    "urlName": "proto-legion-dark-caster-0-ac",
    "url": "http://aqwwiki.wikidot.com/proto-legion-dark-caster-0-ac",
    "name": "Proto Legion Dark Caster (0 AC)",
    "type": "armors",
    "description": "The arcane dark arts have existed since before the march of the Legion. Their craft has since been sharpened by Dage the Evil, bringing ancient forbidden knowledge into a new age.",
    "rarity": "Rare Rarity",
    "tags": [
        "Adventure Coins",
        "Pseudo Rare"
    ],
    "images": [
        "https://imgur.com/bmSWlnF.png",
        "https://imgur.com/9xJVgYB.png"
    ],
    "hash": "acd662bb4cdfee4488b2a9c1b869450d"
}