{
    "urlName": "rainbow-unicorn-kigurumi",
    "url": "http://aqwwiki.wikidot.com/rainbow-unicorn-kigurumi",
    "name": "Rainbow Unicorn Kigurumi",
    "type": "armors",
    "description": "The Chickenlord knows just how much comfort a costume can bring to young and old alike\u2026 though he never says what comfort it brings him. But in this rainbow unicorn kigurumi, you're able to live the dream of fairy tale princesses everywhere.",
    "rarity": "Seasonal Item Rarity",
    "tags": [
        "Adventure Coins",
        "Seasonal"
    ],
    "images": [
        "https://imgur.com/EhwpxSr.png",
        "https://imgur.com/eAwLqaj.png"
    ],
    "hash": "c20d9ea0111ec16de5ece67ca946e49b"
}