{
    "urlName": "proto-champion-of-monsters",
    "url": "http://aqwwiki.wikidot.com/proto-champion-of-monsters",
    "name": "Proto-Champion of Monsters",
    "type": "armors",
    "description": "Aeons before Drakath, this bestial warrior served the Queen of Monsters with a loyalty that could not be shattered.",
    "rarity": "Awesome Rarity",
    "tags": [
        "Adventure Coins"
    ],
    "images": [
        "https://imgur.com/ouKdpns.png"
    ],
    "hash": "cd0fcb08c846cfbb465efbcbb9eb5906"
}