{
    "urlName": "shadow-mayhem-streetwear-non-ac",
    "url": "http://aqwwiki.wikidot.com/shadow-mayhem-streetwear-non-ac",
    "name": "Shadow Mayhem Streetwear (Non-AC)",
    "type": "armors",
    "description": "Between dark goth and and pastel sweetie, you're carving out your own style.",
    "rarity": "Rare Rarity",
    "tags": [
        "Rare"
    ],
    "images": [
        "https://imgur.com/ph0L40r.png",
        "https://imgur.com/2BG1UUL.png"
    ],
    "hash": "f5ffc702e7a22aa13557a4987052babb"
}