{
    "urlName": "warforged-ignisknight",
    "url": "http://aqwwiki.wikidot.com/warforged-ignisknight",
    "name": "Warforged IgnisKnight",
    "type": "armors",
    "description": "The IgnisKnight takes the form of the Horseman of War\u2026from another time and space. War's name always changes, and always returns. Let the masses gather. Force them to their knees so they'll have the strength to fly.",
    "rarity": "Rare Rarity",
    "tags": [
        "Adventure Coins",
        "Pseudo Rare"
    ],
    "images": [
        "https://i.imgur.com/4OQBWoe.png",
        "https://i.imgur.com/mEUEvTn.png"
    ],
    "hash": "f887b54b69d80a4ab4b4eacecd6febcc"
}