{
    "urlName": "banlaoch-beannaithe-locks",
    "url": "http://aqwwiki.wikidot.com/banlaoch-beannaithe-locks",
    "name": "Banlaoch Beannaithe Locks",
    "type": "helmets_&_hoods",
    "description": "Adh Mor Ort, my friend! May you always find victory in battle, a life full of happiness, and even greater rewards than those you seek.",
    "rarity": "Seasonal Item Rarity",
    "tags": [
        "Adventure Coins",
        "Seasonal"
    ],
    "images": [
        "https://i.imgur.com/gUL1t05.png"
    ],
    "hash": "1821a8c64cdb201d8e51ffabf5edbfce"
}