{
    "urlName": "urban-assassin-locks-mask-special",
    "url": "http://aqwwiki.wikidot.com/urban-assassin-locks-mask-special",
    "name": "Urban Assassin Locks + Mask (Special)",
    "type": "helmets_&_hoods",
    "description": "Whoever said that assassins were restricted to long corridors and dark forests have never met these guys before.",
    "rarity": "Seasonal Item Rarity",
    "tags": [
        "Adventure Coins",
        "Seasonal",
        "Special Offer"
    ],
    "images": [
        "https://i.imgur.com/KhxXmd5.png"
    ],
    "hash": "194b3263f3e0b4bb4023b0f7465d6a58"
}