{
    "urlName": "patched-golden-commander-s-hat-0-ac",
    "url": "http://aqwwiki.wikidot.com/patched-golden-commander-s-hat-0-ac",
    "name": "Patched Golden Commander's Hat (0 AC)",
    "type": "helmets_&_hoods",
    "description": "Gold be the only treasure worth searching for! Show your bounty by dressing in this fancy swag.",
    "rarity": "Rare Rarity",
    "tags": [
        "Adventure Coins",
        "Pseudo Rare"
    ],
    "images": [
        "https://i.imgur.com/ehAE44g.png"
    ],
    "hash": "1ed7a3671819860afd3f0a629dcd374b"
}