{
    "urlName": "dragon-ninja-guard-merge",
    "url": "http://aqwwiki.wikidot.com/dragon-ninja-guard-merge",
    "name": "Dragon Ninja Guard (Merge)",
    "type": "helmets_&_hoods",
    "description": "As a Dragon Ninja, you have been entrusted to guard all of Lore from the forces of Chaos\u2026 and Brutalcorn. The gilded guard also helps protect your head. Woohoo double meaning!",
    "rarity": "Rare Rarity",
    "tags": [
        "Adventure Coins",
        "Rare"
    ],
    "images": [],
    "hash": "2fb98afd0ecff3ceb6031c9118ce529b"
}