{
    "urlName": "royal-nereidian-locks-non-ac",
    "url": "http://aqwwiki.wikidot.com/royal-nereidian-locks-non-ac",
    "name": "Royal Nereidian Locks (Non-AC)",
    "type": "helmets_&_hoods",
    "description": "Deep below the waves, an entire civilization flourishes. The Nereidian people rule a vast underwater realm, but one that has never been fully explored by humans.",
    "rarity": "Rare Rarity",
    "tags": [
        "Rare"
    ],
    "images": [
        "https://i.imgur.com/0rY5l3S.png"
    ],
    "hash": "4205dec7d3cb851d48dca60f308fc6e8"
}