{
    "urlName": "voidfiend-symbiote-s-horned-helm-scarf-0-ac",
    "url": "http://aqwwiki.wikidot.com/voidfiend-symbiote-s-horned-helm-scarf-0-ac",
    "name": "Voidfiend Symbiote's Horned Helm + Scarf (0 AC)",
    "type": "helmets_&_hoods",
    "description": "The swirling red-range pattern that pulses through the thin, dark skin of the Voidfiend Symbiote is a sign that the symbiosis with Nulgath's dark energy is complete.",
    "rarity": "Rare Rarity",
    "tags": [
        "Adventure Coins",
        "Pseudo Rare"
    ],
    "images": [
        "https://i.imgur.com/ZyzTHNq.png"
    ],
    "hash": "4518244d3f6992ffa138293a20f7bd4a"
}