{
    "urlName": "dirty-deputy-s-hat",
    "url": "http://aqwwiki.wikidot.com/dirty-deputy-s-hat",
    "name": "Dirty Deputy's Hat",
    "type": "helmets_&_hoods",
    "description": "I will give you a ticket not only for excessively bitting that man to death but also for getting my hat dirty!",
    "rarity": "Seasonal Item Rarity",
    "tags": [
        "Legend",
        "Seasonal",
        "Rare"
    ],
    "images": [
        "http://i.imgur.com/0SZfcNs.png"
    ],
    "hash": "4d02cc723ea2f46fbcb532fde79465fc"
}