{
    "urlName": "glacial-frostelf-crown",
    "url": "http://aqwwiki.wikidot.com/glacial-frostelf-crown",
    "name": "Glacial FrostElf Crown",
    "type": "helmets_&_hoods",
    "description": "The High FrostElf Kings and Queens have ruled over the frosty, frigid Northlands for millennia. This ceremonial regalia is worn for the Winter Moon celebration.",
    "rarity": "Seasonal Item Rarity",
    "tags": [
        "Adventure Coins",
        "Seasonal"
    ],
    "images": [
        "https://i.imgur.com/VDtbphF.png"
    ],
    "hash": "58a31523e1884b268e0a5a901b0c4969"
}