{
    "urlName": "vampirate-hair-scarf",
    "url": "http://aqwwiki.wikidot.com/vampirate-hair-scarf",
    "name": "Vampirate Hair + Scarf",
    "type": "helmets_&_hoods",
    "description": "Just because yer a blood suckin' pillager don't mean ye can't be pretty.",
    "rarity": "Rare Rarity",
    "tags": [
        "Adventure Coins",
        "Rare"
    ],
    "images": [
        "http://aqwwiki.wdfiles.com/local--files/vampirate-hair-scarf/VHS.png"
    ],
    "hash": "5fb1079b9f379af766701bc6dcbf34fb"
}