{
    "urlName": "magitech-dragon-masked-locks-ac",
    "url": "http://aqwwiki.wikidot.com/magitech-dragon-masked-locks-ac",
    "name": "Magitech Dragon Masked Locks (AC)",
    "type": "helmets_&_hoods",
    "description": "Imagine technology that runs on time. But, who's time? What happens when someone runs out of time early? Would you let something like that exist?",
    "rarity": "Rare Rarity",
    "tags": [
        "Adventure Coins",
        "Rare"
    ],
    "images": [
        "https://i.imgur.com/Ejd8fv7.png"
    ],
    "hash": "614dfa5fdaea7067f2a4c10c2e170e1f"
}