{
    "urlName": "honorable-ninja-hood",
    "url": "http://aqwwiki.wikidot.com/honorable-ninja-hood",
    "name": "Honorable Ninja Hood",
    "type": "helmets_&_hoods",
    "description": "When one follows the code of the ninja, one must sacrifice everything for the greated good, only then can you achieve this level of honor.",
    "rarity": "Seasonal Item Rarity",
    "tags": [
        "Adventure Coins",
        "Seasonal"
    ],
    "images": [
        "https://i.imgur.com/BnhPiSL.png"
    ],
    "hash": "6ed6a065ba07515782d175e017335121"
}