{
    "urlName": "enchanted-infernal-underworld-battle-morph",
    "url": "http://aqwwiki.wikidot.com/enchanted-infernal-underworld-battle-morph",
    "name": "Enchanted Infernal Underworld Battle Morph",
    "type": "helmets_&_hoods",
    "description": "Lost souls wander the underworld. Those who retain a measure of their strength and skill may be recruited into the Infernal Underworld Army. They guard the realm itself, unattached to any faction. (Item is CC to Eye)",
    "rarity": "Legendary Item Rarity",
    "tags": [
        "Adventure Coins",
        "Special Offer"
    ],
    "images": [
        "https://i.imgur.com/bDanshW.png"
    ],
    "hash": "792073c82e2f041586a9fca70fdc1d11"
}