{
    "urlName": "j-sixth-mask-ac",
    "url": "http://aqwwiki.wikidot.com/j-sixth-mask-ac",
    "name": "J-Sixth Mask (AC)",
    "type": "helmets_&_hoods",
    "description": "\"It is not necessary to lie to achieve anything of value. A skilled Sixth-Lord is nearly impossible to defeat.\" (This item has color-customizable trim).",
    "rarity": "Seasonal Item Rarity",
    "tags": [
        "Adventure Coins",
        "Seasonal"
    ],
    "images": [
        "https://i.imgur.com/0WXtaYf.png"
    ],
    "hash": "7ee463b2ddb944c22174e4ce3b5f9740"
}