{
    "urlName": "enchanted-bujin-doomknight-hairbun-visage",
    "url": "http://aqwwiki.wikidot.com/enchanted-bujin-doomknight-hairbun-visage",
    "name": "Enchanted Bujin DoomKnight Hairbun Visage",
    "type": "helmets_&_hoods",
    "description": "A courtly yet pragmatic style that gives an air of authority. According to a member of the Shadowscythe, this is how the Crown Princess from another Empire used to wear her hair. (Item is color-customizable.)",
    "rarity": "Rare Rarity",
    "tags": [
        "Adventure Coins",
        "Rare"
    ],
    "images": [
        "https://i.imgur.com/vWVbBkc.png"
    ],
    "hash": "86824081a502a84a00eedc926b0c1d5d"
}