{
    "urlName": "frozen-royalty-locks",
    "url": "http://aqwwiki.wikidot.com/frozen-royalty-locks",
    "name": "Frozen Royalty Locks",
    "type": "helmets_&_hoods",
    "description": "Some may say the control of one's magic relies on emotions or a reflection their inner beasts. If the latter is true, the feeling of getting pricked by an ice monarch's crown is far from cold.",
    "rarity": "Rare Rarity",
    "tags": [
        "Rare"
    ],
    "images": [
        "http://aqwwiki.wdfiles.com/local--files/frozen-royalty-locks/FrozenRoyaltyLocks.png"
    ],
    "hash": "999efe4393db609ba00b9815a8dc829d"
}