{
    "urlName": "flaming-raptor-rider-s-skull",
    "url": "http://aqwwiki.wikidot.com/flaming-raptor-rider-s-skull",
    "name": "Flaming Raptor Rider's Skull",
    "type": "helmets_&_hoods",
    "description": "At night and when around the forces of chaos, the Raptor Rider's skull becomes engulfed in ghostly flame.",
    "rarity": "Rare Rarity",
    "tags": [
        "Adventure Coins",
        "Rare"
    ],
    "images": [
        "http://aqwwiki.wdfiles.com/local--files/flaming-raptor-rider-s-skull/FRRS.png"
    ],
    "hash": "99bf9a19fb988dd951d64006b94a79de"
}