{
    "urlName": "eden-high-formal-locks",
    "url": "http://aqwwiki.wikidot.com/eden-high-formal-locks",
    "name": "Eden High Formal Locks",
    "type": "helmets_&_hoods",
    "description": "Life in Eden is idyllic for the citizens of the Crystallis Administration, and pleasant distractions abound. High Formal events are held regularly for the elite. Should you be invited, you will require a Protocol Master's assistance.",
    "rarity": "Awesome Rarity",
    "tags": [
        "Adventure Coins"
    ],
    "images": [
        "https://i.imgur.com/TJPeyK5.png"
    ],
    "hash": "a0c6290b4d32b6e9db2458bf05c9542e"
}