{
    "urlName": "island-retreat-morph-hair-ac",
    "url": "http://aqwwiki.wikidot.com/island-retreat-morph-hair-ac",
    "name": "Island Retreat Morph Hair (AC)",
    "type": "helmets_&_hoods",
    "description": "Description: Everybody needs to get away after a long season of waging war, boss battles, and hauling home loot\u2026 and a hidden island retreat is the BEST place to /rest, recoup, and re-energize.",
    "rarity": "Rare Rarity",
    "tags": [
        "Adventure Coins",
        "Rare"
    ],
    "images": [
        "https://i.imgur.com/yAlVqLC.png"
    ],
    "hash": "a2eb18f2fb8474136b6f4221af866d5b"
}