{
    "urlName": "underworld-eminence-hood-ac",
    "url": "http://aqwwiki.wikidot.com/underworld-eminence-hood-ac",
    "name": "Underworld Eminence Hood (AC)",
    "type": "helmets_&_hoods",
    "description": "The Titan has the ability to rip open a hole to the surface of Lore with its bare hands. To prevent complete destruction, it's kept chained in the Phlegethon Dungeons\u2026until the time is right.",
    "rarity": "Rare Rarity",
    "tags": [
        "Adventure Coins",
        "Rare"
    ],
    "images": [
        "https://i.imgur.com/6K07YWn.png"
    ],
    "hash": "b7e1b21f33dcdc72fe283f473dd2f501"
}