{
    "urlName": "zhu-ronin-chibi-pig-hair-morph",
    "url": "http://aqwwiki.wikidot.com/zhu-ronin-chibi-pig-hair-morph",
    "name": "Zhu Ronin Chibi Pig Hair Morph",
    "type": "helmets_&_hoods",
    "description": "A ronin is a samurai with no master but these follow the ancient ways of the Zhu.",
    "rarity": "Seasonal Item Rarity",
    "tags": [
        "Legend",
        "Seasonal"
    ],
    "images": [
        "https://imgur.com/UCbSF2B.png"
    ],
    "hash": "bd6e9b86ccfacc5bf6226e16c478a8da"
}