{
    "urlName": "celestial-avenger-s-faceplate",
    "url": "http://aqwwiki.wikidot.com/celestial-avenger-s-faceplate",
    "name": "Celestial Avenger's Faceplate",
    "type": "helmets_&_hoods",
    "description": "With the assistance of the soft, sapphire wings, fly high and don't look down. The bright sky will reflect the helm gracefully unless it's a rainy day. Then it will be the only object that shines.",
    "rarity": "Rare Rarity",
    "tags": [
        "Adventure Coins",
        "Rare"
    ],
    "images": [
        "http://aqwwiki.wdfiles.com/local--files/celestial-avenger-s-faceplate/CelestialAvenger'sFaceplate.png"
    ],
    "hash": "c551c4853a66a5c240a6a3445900cdf9"
}