{
    "urlName": "chaos-dragon-tricorn-beard-ac",
    "url": "http://aqwwiki.wikidot.com/chaos-dragon-tricorn-beard-ac",
    "name": "Chaos Dragon Tricorn + Beard (AC)",
    "type": "helmets_&_hoods",
    "description": "YARRRR! Only a true Chaos Dragon Pirate could steal as many gems as you have right out from under the noses of those mountain dwaves.",
    "rarity": "Seasonal Item Rarity",
    "tags": [
        "Adventure Coins",
        "Seasonal"
    ],
    "images": [
        "https://imgur.com/mZHtt4q.png"
    ],
    "hash": "c83c14fc338bec3d26695de2ae8c67c6"
}