{
    "urlName": "permafrost-sidhe-beard-0-ac",
    "url": "http://aqwwiki.wikidot.com/permafrost-sidhe-beard-0-ac",
    "name": "Permafrost Sidhe Beard (0 AC)",
    "type": "helmets_&_hoods",
    "description": "The Permafrost Sidhe of the Winter Court hold festivals filled with song and dance. Rimeblossoms and frozen humans decorate their icefields.",
    "rarity": "Rare Rarity",
    "tags": [
        "Adventure Coins",
        "Pseudo Rare"
    ],
    "images": [
        "https://i.imgur.com/m3QKg3p.png"
    ],
    "hash": "cf07e8803bb991e5170759450cf8198c"
}