{
    "urlName": "apophis-medjai-locks",
    "url": "http://aqwwiki.wikidot.com/apophis-medjai-locks",
    "name": "Apophis Medjai Locks",
    "type": "helmets_&_hoods",
    "description": "When Pharaoh Neith elevated a Shadow to the level of a god, almost all of her subjects turned traitor. Apophis' Medjai hunted them relentlessly, dying the sands red.",
    "rarity": "Awesome Rarity",
    "tags": [
        "Adventure Coins"
    ],
    "images": [
        "https://i.imgur.com/2L7Hw10.png"
    ],
    "hash": "d37493f990a0fcfa36b9289732ab633c"
}