{
    "urlName": "chaotic-vamp-faceplate",
    "url": "http://aqwwiki.wikidot.com/chaotic-vamp-faceplate",
    "name": "Chaotic Vamp Faceplate",
    "type": "helmets_&_hoods",
    "description": "Covering the majority of the nose and mouth, this faceplate is a must for aggressive Vampires who like to nibble on everyone and everything.",
    "rarity": "Weird Rarity",
    "tags": [
        "Legend"
    ],
    "images": [
        "https://i.imgur.com/J6ZaH0p.png"
    ],
    "hash": "e2984e96ab7b2823086f38faca63c88e"
}