{
    "urlName": "bonebreaker-commander-s-hair-0-ac",
    "url": "http://aqwwiki.wikidot.com/bonebreaker-commander-s-hair-0-ac",
    "name": "Bonebreaker Commander's Hair (0 AC)",
    "type": "helmets_&_hoods",
    "description": "Crossing the sea to find more bones to break. We're comin' fer ya!",
    "rarity": "Rare Rarity",
    "tags": [
        "Adventure Coins",
        "Pseudo Rare"
    ],
    "images": [
        "https://imgur.com/NLrPO75.png"
    ],
    "hash": "e61badada6960e28bed4c6aaf8552d28"
}