{
    "urlName": "dark-frostval-drakath-morph",
    "url": "http://aqwwiki.wikidot.com/dark-frostval-drakath-morph",
    "name": "Dark Frostval Drakath Morph",
    "type": "helmets_&_hoods",
    "description": "Deep in the heart of the frozen Northlands, Chaos power lays dormant, trapped under dark ice\u2026 waiting for its Champion to return and unleash it.",
    "rarity": "Rare Rarity",
    "tags": [
        "Adventure Coins",
        "Pseudo Rare"
    ],
    "images": [
        "https://i.imgur.com/MiQ3EvU.png"
    ],
    "hash": "ed030233f4e0e8f69d606eb0186b670c"
}