{
    "urlName": "marauder-s-hair",
    "url": "http://aqwwiki.wikidot.com/marauder-s-hair",
    "name": "Marauder's Hair",
    "type": "helmets_&_hoods",
    "description": "Under a black flag we sail and the sea shall be our empire! No ship be safe from our guns, an' glory an' gold be the treasure we seek.",
    "rarity": "Seasonal Item Rarity",
    "tags": [
        "Adventure Coins",
        "Seasonal"
    ],
    "images": [
        "https://i.imgur.com/1KFBCE0.png"
    ],
    "hash": "f3608c25ec10f84f317bc8d1760c5305"
}