{
    "urlName": "eternal-dark-caster-locks",
    "url": "http://aqwwiki.wikidot.com/eternal-dark-caster-locks",
    "name": "Eternal Dark Caster Locks",
    "type": "helmets_&_hoods",
    "description": "With every spell you cast, another soul joins the ranks of the Undead Legion\u2026",
    "rarity": "Boss Drop Rarity",
    "tags": [
        "Adventure Coins",
        "Seasonal"
    ],
    "images": [
        "http://i.imgur.com/G6hHKWm.png"
    ],
    "hash": "f437c422d3ed7e4c43865faa4a31fe15"
}