{
    "urlName": "crested-deathmask",
    "url": "http://aqwwiki.wikidot.com/crested-deathmask",
    "name": "Crested Deathmask",
    "type": "helmets_&_hoods",
    "description": "Because it is used to cleverly disguise shapeless shadow elementals, this is one light onyx helmet that a warlord from deep within the underworld will praise and be proud of.",
    "rarity": "Rare Rarity",
    "tags": [
        "Adventure Coins",
        "Pseudo Rare",
        "Special Offer"
    ],
    "images": [
        "http://aqwwiki.wdfiles.com/local--files/crested-deathmask/CD.png"
    ],
    "hash": "f61fa8ef9679484ea3ed4364edd2ebfd"
}