{
    "urlName": "archfiend-dragonlord-s-visor",
    "url": "http://aqwwiki.wikidot.com/archfiend-dragonlord-s-visor",
    "name": "Archfiend DragonLord's Visor",
    "type": "helmets_&_hoods",
    "description": "The mark of the dragon is burned showing your allegiance.",
    "rarity": "Rare Rarity",
    "tags": [
        "Adventure Coins",
        "Pseudo Rare",
        "Special Offer"
    ],
    "images": [
        "https://i.imgur.com/oox8tAk.png"
    ],
    "hash": "f6b2d922c45d71c4b8f5da31a94d1a46"
}