{
    "urlName": "gothic-alchemist-hood-locks",
    "url": "http://aqwwiki.wikidot.com/gothic-alchemist-hood-locks",
    "name": "Gothic Alchemist Hood + Locks",
    "type": "helmets_&_hoods",
    "description": "Recruited by Big Daddy, these alchemists are entrusted to brew handmade love potions \u2026until they accidentally picked the wrong ingredients.",
    "rarity": "Rare Rarity",
    "tags": [
        "Adventure Coins",
        "Rare"
    ],
    "images": [
        "https://i.imgur.com/r063dZS.png"
    ],
    "hash": "febe6eaca1186eedd548022ea2ad9212"
}