{
    "urlName": "vindicator-scout-s-hat-locks",
    "url": "http://aqwwiki.wikidot.com/vindicator-scout-s-hat-locks",
    "name": "Vindicator Scout's Hat + Locks",
    "type": "helmets_&_hoods",
    "description": "Many of the Dawn Vindicators were recruited very young. Whether they did so with the blessings of their homes or disappeared one day, few will recognize them when they return in white and gold.",
    "rarity": "Awesome Rarity",
    "tags": [
        "Adventure Coins"
    ],
    "images": [
        "https://i.imgur.com/b1TpMkA.png"
    ],
    "hash": "ffe490c9cd1664b1f776de61e79d78fe"
}